tw_source_finder/__init__.py
tw_source_finder/adjust_reference_position.py
tw_source_finder/beam_to_pixels.py
tw_source_finder/breizorro_extract.py
tw_source_finder/calculate_source_parms.py
tw_source_finder/check_array.py
tw_source_finder/combine_images.py
tw_source_finder/conv_image.py
tw_source_finder/coords.py
tw_source_finder/cosmocalc.py
tw_source_finder/equipartition.py
tw_source_finder/generate_manual_polygon.py
tw_source_finder/generate_mask_polygons.py
tw_source_finder/generate_morphology_image.py
tw_source_finder/get_alasky_image.py
tw_source_finder/get_galaxy_parameters.py
tw_source_finder/get_morphology_images.py
tw_source_finder/image_math.py
tw_source_finder/inpainter.py
tw_source_finder/insert_beam_parameters.py
tw_source_finder/larrys_script.py
tw_source_finder/make_morphology_mask.py
tw_source_finder/morphology_reduction_script.md
tw_source_finder/process_polygon_data.py
tw_source_finder/pyheal.py
tw_source_finder/read_input_table.py
tw_source_finder/reproject_images.py
tw_source_finder/scripts/__init__.py
tw_source_finder/scripts/get_simple_source_list.py
tw_source_finder-1.0.0.dist-info/WHEEL
tw_source_finder-1.0.0.dist-info/METADATA
tw_source_finder-1.0.0.dist-info/entry_points.txt
tw_source_finder-1.0.0.dist-info/LICENSE
tw_source_finder-1.0.0.dist-info/RECORD
