Metadata-Version: 2.1
Name: tw-source-finder
Version: 1.0.0
Summary: super-fast source finder routine using polygon based approach
License: MIT
Author: Tony Willis
Author-email: tony.willis.research@gmail.com
Maintainer: Tony Willis
Maintainer-email: tony.willis.research@gmail.com
Requires-Python: >=3.8,<4.0
Classifier: Development Status :: 4 - Beta
Classifier: Intended Audience :: Science/Research
Classifier: License :: OSI Approved :: MIT License
Classifier: Natural Language :: English
Classifier: Programming Language :: Python :: 3
Classifier: Programming Language :: Python :: 3.8
Classifier: Programming Language :: Python :: 3.9
Classifier: Programming Language :: Python :: 3.10
Classifier: Programming Language :: Python :: 3.11
Classifier: Programming Language :: Python :: 3
Classifier: Programming Language :: Python :: 3.9
Classifier: Topic :: Scientific/Engineering :: Astronomy
Requires-Dist: astropy (>=5.1,<6.0)
Requires-Dist: reproject (>=0.9.1,<0.10.0)
Requires-Dist: scikit-image (>=0.19.3,<0.20.0)
Requires-Dist: shapely (>=1.8.5.post1,<2.0.0)
